LICENSE
MANIFEST.in
README.md
requirements.txt
setup.py
action/__init__.py
action/client.py
action/db.py
action/emitter.py
action/event.py
actiondb.egg-info/PKG-INFO
actiondb.egg-info/SOURCES.txt
actiondb.egg-info/dependency_links.txt
actiondb.egg-info/requires.txt
actiondb.egg-info/top_level.txt